README.md
setup.cfg
setup.py
rethreader/__init__.py
rethreader/_rethreader.py
rethreader.egg-info/PKG-INFO
rethreader.egg-info/SOURCES.txt
rethreader.egg-info/dependency_links.txt
rethreader.egg-info/top_level.txt