Metadata-Version: 1.1
Name: rethreader
Version: 1.0.2
Summary: Controlled multi-processing
Home-page: https://github.com/ettoc00/rethreader
Author: Ettore Cesari
Author-email: ettore.cesari@yahoo.it
License: MIT
Download-URL: https://github.com/ettoc00/rethreader/archive/1.0.2.tar.gz
Keywords: thread,multi,processing
Platform: UNKNOWN
Classifier: Development Status :: 3 - Alpha
Classifier: Intended Audience :: Developers
Classifier: Topic :: Software Development :: Build Tools
Classifier: License :: OSI Approved :: MIT License
Classifier: Programming Language :: Python :: 3
Classifier: Programming Language :: Python :: 3.4
Classifier: Programming Language :: Python :: 3.5
Classifier: Programming Language :: Python :: 3.6
Classifier: Programming Language :: Python :: 3.7
Classifier: Programming Language :: Python :: 3.8
